<?xml version="1.0" encoding="utf-8"?>
<!DOCTYPE hibernate-mapping PUBLIC "-//Hibernate/Hibernate Mapping DTD 3.0//EN"
"http://hibernate.sourceforge.net/hibernate-mapping-3.0.dtd">
<!-- 
    Mapping file autogenerated by MyEclipse Persistence Tools
-->
<hibernate-mapping>
    <class name="com.liyun.car.activity.entity.CmsActivityInfo" table="cms_activity_info" >
        <id name="acttCode" type="java.lang.String">
            <column name="actt_Code"/>
        </id>
        <property name="acttNm" type="java.lang.String">
            <column name="actt_Nm"></column>
        </property>
        <property name="subParamEn" type="java.lang.String">
            <column name="sub_param_en"></column>
        </property>
        <property name="topParamEn" type="java.lang.String">
            <column name="top_param_en"></column>
        </property>
        <property name="subParamNm" type="java.lang.String">
            <column name="sub_param_nm"></column>
        </property>
        <property name="acttCyc" type="ActivityCycleEnum">
            <column name="actt_cyc"></column>
        </property>
        <property name="acttTyp" type="java.lang.String">
            <column name="actt_typ"></column>
        </property>
        <property name="isDealer" type="BooleanEnum">
            <column name="is_dealer"></column>
        </property>
        <property name="acttDesc" type="java.lang.String">
            <column name="actt_desc"></column>
        </property>
        <property name="stt" type="ActivityStatusEnum">
            <column name="stt"></column>
        </property>
        <property name="acttBegin" type="java.sql.Timestamp">
            <column name="actt_begin"></column>
        </property>
        <property name="acttEnd" type="java.sql.Timestamp">
            <column name="actt_end"></column>
        </property>
        <bag name="dealers" table="cms_activity_dealer" lazy="true" cascade="all-delete-orphan" inverse="true">
            <key>
                <column name="actt_code" not-null="true"/>
            </key>
            <one-to-many class="com.liyun.car.activity.entity.CmsActivityDealer" />
        </bag>
        <bag name="activityRules" table="cms_activity_rule" lazy="true" cascade="all-delete-orphan" inverse="true">
            <key>
                <column name="actt_code" not-null="true"/>
            </key>
            <one-to-many class="com.liyun.car.activity.entity.CmsActivityRule" />
        </bag>
    </class>
</hibernate-mapping>
