<?xml version="1.0" encoding="utf-8"?>
<!DOCTYPE hibernate-mapping PUBLIC "-//Hibernate/Hibernate Mapping DTD 3.0//EN"
"http://hibernate.sourceforge.net/hibernate-mapping-3.0.dtd">
<!-- 
    Mapping file autogenerated by MyEclipse Persistence Tools
-->
<hibernate-mapping>
    <class name="com.liyun.car.activity.entity.CmsDealerRuleProp" table="cms_dealer_rule_prop" >
        <id name="id" type="java.lang.Integer">
            <column name="id"/>
            <generator class="identity" />
        </id>
        <many-to-one name="rule" class="com.liyun.car.activity.entity.CmsActivityRule" insert="true" update="true" outer-join="true">
        	<column name="rule_id"></column>
        </many-to-one>
        <property name="isOld" type="java.lang.String">
            <column name="is_old"></column>
        </property>
        <property name="carTyp" type="java.lang.String">
            <column name="car_typ"></column>
        </property>
        <property name="cyc" type="java.lang.String">
            <column name="cyc"></column>
        </property>
        <property name="reachTyp" type="java.lang.String">
            <column name="reach_typ"></column>
        </property>
        <property name="propValue" type="java.lang.String">
            <column name="prop_value"></column>
        </property>
    </class>
</hibernate-mapping>
